django_requestlogging/__init__.py
django_requestlogging/logging_filters.py
django_requestlogging/middleware.py
django_requestlogging/models.py
django_requestlogging/tests.py
django_requestlogging_redux-1.2.0.dist-info/DESCRIPTION.rst
django_requestlogging_redux-1.2.0.dist-info/METADATA
django_requestlogging_redux-1.2.0.dist-info/RECORD
django_requestlogging_redux-1.2.0.dist-info/WHEEL
django_requestlogging_redux-1.2.0.dist-info/metadata.json
django_requestlogging_redux-1.2.0.dist-info/top_level.txt
